dtplib/__init__.py
dtplib/client.py
dtplib/server.py
dtplib/util.py
dtplib-1.2.1.dist-info/LICENSE
dtplib-1.2.1.dist-info/METADATA
dtplib-1.2.1.dist-info/WHEEL
dtplib-1.2.1.dist-info/top_level.txt
dtplib-1.2.1.dist-info/RECORD
