Metadata-Version: 2.1
Name: dtplib
Version: 1.2.1
Summary: A cross platform networking library written in Python
Home-page: https://github.com/WKHAllen/dtplib
Author: Will Allen
Author-email: wkhallen@gmail.com
License: MIT
Keywords: networking,websocket,socket,server,client
Platform: UNKNOWN
Classifier: Intended Audience :: Developers
Classifier: Topic :: Internet
Classifier: Topic :: Software Development :: Libraries :: Application Frameworks
Classifier: License :: OSI Approved :: MIT License
Classifier: Programming Language :: Python
Classifier: Programming Language :: Python :: 3
Classifier: Programming Language :: Python :: 3.5
Classifier: Programming Language :: Python :: 3.6
Classifier: Programming Language :: Python :: 3.7
Classifier: Programming Language :: Python :: 3.8
Requires-Dist: compressdir
Requires-Dist: cryptography
Requires-Dist: rsa
